data_watchtower/__init__.py
data_watchtower/api/__init__.py
data_watchtower/api/handlers/__init__.py
data_watchtower/api/handlers/base.py
data_watchtower/api/handlers/data_loader.py
data_watchtower/api/handlers/watchtower.py
data_watchtower/api/server.py
data_watchtower/api/url.py
data_watchtower/core/__init__.py
data_watchtower/core/base.py
data_watchtower/core/data_loaders.py
data_watchtower/core/macro.py
data_watchtower/core/validators.py
data_watchtower/core/watchtower.py
data_watchtower/model/__init__.py
data_watchtower/model/models.py
data_watchtower/model/services.py
data_watchtower/utils.py
data_watchtower-0.0.5.dist-info/LICENSE
data_watchtower-0.0.5.dist-info/METADATA
data_watchtower-0.0.5.dist-info/WHEEL
data_watchtower-0.0.5.dist-info/RECORD
