Metadata-Version: 2.1
Name: data-watchtower
Version: 0.0.5
Summary: Data quality inspection tool. Identify issues before your CTO detects them!
Home-page: https://github.com/acracker/data_watchtower
License: MIT
Author: acracker
Author-email: acracker@163.com
Requires-Python: >=3.7.1,<4.0.0
Classifier: License :: OSI Approved :: MIT License
Classifier: Programming Language :: Python :: 3
Classifier: Programming Language :: Python :: 3.8
Classifier: Programming Language :: Python :: 3.9
Classifier: Programming Language :: Python :: 3.10
Classifier: Programming Language :: Python :: 3.11
Classifier: Programming Language :: Python :: 3.12
Requires-Dist: apischema (>=0.18.1,<0.19.0)
Requires-Dist: attrs (>=23.2.0,<24.0.0)
Requires-Dist: connectorx (==0.3.1) ; python_version < "3.8"
Requires-Dist: connectorx (>=0.3.2,<0.4.0) ; python_version >= "3.8"
Requires-Dist: pandas (>=1.3.0,<2.0.0) ; python_version < "3.10"
Requires-Dist: pandas (>=2.1.0,<3.0.0) ; python_version >= "3.10"
Requires-Dist: peewee (>=3.17.3,<4.0.0)
Requires-Dist: polars (==0.18.4) ; python_version < "3.8"
Requires-Dist: polars (>=0.20.23,<0.21.0) ; python_version >= "3.8"
Requires-Dist: pyarrow (>=12.0.1,<13.0.0) ; python_version < "3.8"
Requires-Dist: pyarrow (>=16.0.0,<17.0.0) ; python_version >= "3.8"
Requires-Dist: shortuuid (>=1.0.13,<2.0.0)
Requires-Dist: tornado (>=6.2,<7.0) ; python_version < "3.8"
Requires-Dist: tornado (>=6.4,<7.0) ; python_version >= "3.8"
Project-URL: Repository, https://github.com/acracker/data_watchtower
